{
  "project_info": {
    "project_number": "763302326702",
    "project_id": "pioappdiego",
    "storage_bucket": "pioappdiego.firebasestorage.app"
  },
  "client": [
    {
      "client_info": {
        "mobilesdk_app_id": "1:763302326702:android:f8060d193e18f7c768183f",
        "android_client_info": {
          "package_name": "pio_app.diego"
        }
      },
      "oauth_client": [],
      "api_key": [
        {
          "current_key": "AIzaSyA4Kdp1vAEyBG7GkIC2Qs5n6wZ_8ALjMXA"
        }
      ],
      "services": {
        "appinvite_service": {
          "other_platform_oauth_client": []
        }
      }
    }
  ],
  "configuration_version": "1"
}